LICENSE
MANIFEST.in
README.rst
requirements.txt
setup.py
bin/django-cms
cms_site/__init__.py
cms_site/gettext_overrides.py
cms_site/settings.py
cms_site/urls.py
cms_site/wsgi.py
cms_site/locale/cs/LC_MESSAGES/django.mo
cms_site/locale/cs/LC_MESSAGES/django.po
cms_site/templates/default.html
django_cms_site.egg-info/PKG-INFO
django_cms_site.egg-info/SOURCES.txt
django_cms_site.egg-info/dependency_links.txt
django_cms_site.egg-info/requires.txt
django_cms_site.egg-info/top_level.txt